{
  "source_name": "Williams College Museum of Art", 
  "classification": "WCMA-PHOTO", 
  "credit_line": "Gift of Tennyson and Fern Schad", 
  "period": "", 
  "creation_date": "no date", 
  "creation_date_earliest": "1922", 
  "culture": "", 
  "portfolio": "", 
  "paper_support": "", 
  "id": "6340", 
  "catalogue_raisonne": "", 
  "dimensions": "sheet: 13 15/16 x 16 13/16 in. (35.4 x 42.7 cm)\nimage: 4 1/4 x 14 7/8 in. (10.8 x 37.8 cm)", 
  "title": "Untitled", 
  "creation_date_latest": "1992", 
  "filename": "92_22_10.jpg", 
  "object_name": "photograph", 
  "marks": "", 
  "department": "WCMA", 
  "ULAN": "500000873", 
  "medium": "dye transfer print", 
  "description": "", 
  "inscriptions": "verso l.l. in red pencil: 9 [underlined]; l.r. in pencil: 500:5:44.13", 
  "accession_date": "1992-01-01", 
  "accession_number": "92.22.10", 
  "signed": "", 
  "maker": "Harry Morey Callahan"
}