{
  "source_name": "Williams College Museum of Art", 
  "classification": "WCMA-PRINTS", 
  "credit_line": "Gift of Martin J. Oppenheimer", 
  "period": "", 
  "creation_date": "1976", 
  "creation_date_earliest": "1976", 
  "culture": "", 
  "portfolio": "", 
  "paper_support": "", 
  "id": "19266", 
  "catalogue_raisonne": "", 
  "dimensions": "Overall: 38 3/16 x 24 15/16 in. (97 x 63.3 cm)", 
  "title": "Vertical green, blue and black violin (from Romantic Suite)", 
  "creation_date_latest": "1976", 
  "filename": "82_21_2_E.jpg", 
  "object_name": "print", 
  "marks": "", 
  "department": "WCMA", 
  "ULAN": "500003632", 
  "medium": "color photo lithograph on paper", 
  "description": "", 
  "inscriptions": "l.r. in pencil: Arman", 
  "accession_date": "1982-01-01", 
  "accession_number": "82.21.2.E", 
  "signed": "", 
  "maker": "Arman (Armand Fernandez)"
}