{
  "source_name": "Williams College Museum of Art", 
  "classification": "WCMA-PRINTS", 
  "credit_line": "Gift of Mabel Nast Crawford and Cyril Nast", 
  "period": "", 
  "creation_date": "December 31, 1890", 
  "creation_date_earliest": "1890", 
  "culture": "", 
  "portfolio": "", 
  "paper_support": "", 
  "id": "3235", 
  "catalogue_raisonne": "", 
  "dimensions": "Overall: 8 5/8 x 9 1/16 in. (21.9 x 23 cm)", 
  "title": "The Stewart of St. Nickolas in the Senate (Artist Nast's Christmas Greeting to Senator Stewart)", 
  "creation_date_latest": "1890", 
  "filename": "IMG_49.17.81.jpg", 
  "object_name": "print | newspaper", 
  "marks": "", 
  "department": "WCMA", 
  "ULAN": "500026650", 
  "medium": "print on paper", 
  "description": "", 
  "inscriptions": "in plate l.r.: Th:Nast.", 
  "accession_date": "1949-01-01", 
  "accession_number": "49.17.81", 
  "signed": "", 
  "maker": "Thomas Nast"
}