{
  "source_name": "Williams College Museum of Art", 
  "classification": "WCMA-DEC ARTS", 
  "credit_line": "Gift of Mrs. Davenport West", 
  "period": "", 
  "creation_date": "1743", 
  "creation_date_earliest": "1743", 
  "culture": "", 
  "portfolio": "", 
  "paper_support": "", 
  "id": "13147", 
  "catalogue_raisonne": "", 
  "dimensions": "Overall: 10 7/16 x 8 11/16 in. (26.5 x 22 cm)\ncircumference: 13 in. (33 cm)\nrim: 4 3/4 in. (12 cm)", 
  "title": "Flagon", 
  "creation_date_latest": "1743", 
  "filename": "", 
  "object_name": "flagon", 
  "marks": "", 
  "department": "WCMA", 
  "ULAN": "not found", 
  "medium": "pewter", 
  "description": "", 
  "inscriptions": "engraved on lid in German (translated): Presented to: the Church at Groitzschen by Christian Friedrich Freiesleben, Government-attorney at Bera and director of Justice at Nauendorff Anno 1743; stamped on handle: [artist's seal]", 
  "accession_date": "1962-01-01", 
  "accession_number": "62.12", 
  "signed": "", 
  "maker": "Anonymous (German)"
}