{
  "source_name": "Williams College Museum of Art", 
  "classification": "WCMA-Prendergast", 
  "credit_line": "Gift of Mrs. Charles Prendergast", 
  "period": "", 
  "creation_date": "no date", 
  "creation_date_earliest": "1858", 
  "culture": "", 
  "portfolio": "", 
  "paper_support": "", 
  "id": "8051", 
  "catalogue_raisonne": "", 
  "dimensions": "", 
  "title": "Three pages of calendar bound together (January-March)", 
  "creation_date_latest": "1924", 
  "filename": "", 
  "object_name": "drawing", 
  "marks": "", 
  "department": "WCMA", 
  "ULAN": "not found", 
  "medium": "paper", 
  "description": "", 
  "inscriptions": "", 
  "accession_date": "1985-01-01", 
  "accession_number": "85.26.25", 
  "signed": "", 
  "maker": "Maurice Brazil Prendergast"
}