{
  "source_name": "Williams College Museum of Art", 
  "classification": "WCMA-Prendergast", 
  "credit_line": "Williams College Museum of Art, Gift of Mrs. Charles Prendergast", 
  "period": "", 
  "creation_date": "ca. 1900-1905", 
  "creation_date_earliest": "1900", 
  "culture": "", 
  "portfolio": "", 
  "paper_support": "", 
  "id": "7089", 
  "catalogue_raisonne": "CMO #1481", 
  "dimensions": "6 7/8 x 4 x 7/8 in. (17.5 x 10.2 x 2.2 cm)\nStorage custom slipcase: 19.4 x 12.1 x 4.1 cm (7 5/8 x 4 3/4 x 1 5/8 in.)", 
  "title": "\"Sketchbook\"", 
  "creation_date_latest": "1905", 
  "filename": "85_26_9_cover.jpg", 
  "object_name": "sketchbook", 
  "marks": "", 
  "department": "WCMA", 
  "ULAN": "not found", 
  "medium": "sketchbook", 
  "description": "95 pencil drawings on lined paper", 
  "inscriptions": "", 
  "accession_date": "1985-01-01", 
  "accession_number": "85.26.9", 
  "signed": "", 
  "maker": "Maurice Brazil Prendergast"
}