{
  "source_name": "Williams College Museum of Art", 
  "classification": "WCMA-PRINTS", 
  "credit_line": "Anonymous gift", 
  "period": "", 
  "creation_date": "no date", 
  "creation_date_earliest": "0", 
  "culture": "", 
  "portfolio": "", 
  "paper_support": "", 
  "id": "6515", 
  "catalogue_raisonne": "", 
  "dimensions": "image: 9 3/16 x 12 5/8 in. (23.3 x 32.1 cm)\nsheet: 16 9/16 x 22 7/16 in. (42 x 57 cm)", 
  "title": "Vue du Jardin du Palais Royal", 
  "creation_date_latest": "0", 
  "filename": "IMG_92.5.171.C.jpg", 
  "object_name": "print", 
  "marks": "", 
  "department": "WCMA", 
  "ULAN": "not found", 
  "medium": "lithograph on paper", 
  "description": "", 
  "inscriptions": "l.c. stamped: [collector's stamp]", 
  "accession_date": "1992-01-01", 
  "accession_number": "92.5.171.C", 
  "signed": "", 
  "maker": "Jules Arnout"
}