{
  "source_name": "Williams College Museum of Art", 
  "classification": "WCMA-PRINTS", 
  "credit_line": "Gift of James F. White", 
  "period": "", 
  "creation_date": "2005", 
  "creation_date_earliest": "2005", 
  "culture": "", 
  "portfolio": "", 
  "paper_support": "", 
  "id": "28228", 
  "catalogue_raisonne": "", 
  "dimensions": "plate: 7 1/8 x 9 1/2 in. (18.1 x 24.1 cm)\nsheet: 10 7/8 x 15 in. (27.6 x 38.1 cm)", 
  "title": "Pages from a sketchbook: #4", 
  "creation_date_latest": "2005", 
  "filename": "M_2012_4_2.jpg", 
  "object_name": "print", 
  "marks": "", 
  "department": "WCMA", 
  "ULAN": "500104369", 
  "medium": "drypoint", 
  "description": "", 
  "inscriptions": "Signed below plate in pencil: 25/50 Kipniss\nSigned at bottom right in sheet in pencil: Pages from a sketchbook: #4\nEmbossed at bottom left in sheet", 
  "accession_date": "2012-04-06", 
  "accession_number": "M.2012.4.2", 
  "signed": "", 
  "maker": "Robert Kipniss"
}