{
  "source_name": "Williams College Museum of Art", 
  "classification": "WCMA-PRINTS", 
  "credit_line": "Gift of Milton C. Rose, Class of 1927", 
  "period": "", 
  "creation_date": "probably after 1950", 
  "creation_date_earliest": "1950", 
  "culture": "", 
  "portfolio": "", 
  "paper_support": "", 
  "id": "4917", 
  "catalogue_raisonne": "", 
  "dimensions": "sheet: 13 3/4 x 18 in. (35 x 45.7 cm)\nplate: 8 1/8 x 10 15/16 in. (20.7 x 27.8 cm)", 
  "title": "Untitled", 
  "creation_date_latest": "1981", 
  "filename": "81_31_60.jpg", 
  "object_name": "print", 
  "marks": "", 
  "department": "WCMA", 
  "ULAN": "not found", 
  "medium": "embossed print", 
  "description": "", 
  "inscriptions": "l.r. in pencil: Molin; verso l.l. in ink: [print club stamp]", 
  "accession_date": "1981-01-01", 
  "accession_number": "81.31.60", 
  "signed": "", 
  "maker": "Brita Molin"
}