{
  "source_name": "Williams College Museum of Art", 
  "classification": "WCMA-PAINTING", 
  "credit_line": "Bequest of Lawrence H. Bloedel, Class of 1923, Courtesy of the Whitney Museum of American Art", 
  "period": "", 
  "creation_date": "1961", 
  "creation_date_earliest": "1961", 
  "culture": "", 
  "portfolio": "", 
  "paper_support": "", 
  "id": "5874", 
  "catalogue_raisonne": "", 
  "dimensions": "Overall: 24 1/8 x 30 13/16 in. (61.2 x 78.2 cm)\nframe: 24 13/16 x 30 13/16 in. (63 x 78.2 cm)", 
  "title": "The Meeting", 
  "creation_date_latest": "1961", 
  "filename": "85_40_6.jpg", 
  "object_name": "painting", 
  "marks": "", 
  "department": "WCMA", 
  "ULAN": "500028137", 
  "medium": "oil on canvas", 
  "description": "", 
  "inscriptions": "l.r. in oil: Oliveira 61", 
  "accession_date": "1985-01-01", 
  "accession_number": "85.40.6", 
  "signed": "", 
  "maker": "Nathan Oliveira"
}