{
  "source_name": "Williams College Museum of Art", 
  "classification": "WCMA-PRINTS", 
  "credit_line": "Gift of Exit Art", 
  "period": "", 
  "creation_date": "2011", 
  "creation_date_earliest": "2011", 
  "culture": "", 
  "portfolio": "", 
  "paper_support": "", 
  "id": "29293", 
  "catalogue_raisonne": "", 
  "dimensions": "22 x 30 in. (55.9 x 76.2 cm)", 
  "title": "Mad Era (from \"2011: SEA (Social Environmental Aesthetics)\")", 
  "creation_date_latest": "2011", 
  "filename": "M_2012_15_7_B.jpg", 
  "object_name": "print", 
  "marks": "", 
  "department": "WCMA", 
  "ULAN": "not found", 
  "medium": "offset screen print and xylograph with mahogany on Sihl 320 grams", 
  "description": "", 
  "inscriptions": "", 
  "accession_date": "2012-10-17", 
  "accession_number": "M.2012.15.7.B", 
  "signed": "", 
  "maker": "Charles Juhasz-Alvarado"
}