{
  "source_name": "Williams College Museum of Art", 
  "classification": "WCMA-Prendergast", 
  "credit_line": "Williams College Museum of Art, Prendergast Archive and Study Center, Gift of Mrs. Charles Prendergast", 
  "period": "", 
  "creation_date": "1938", 
  "creation_date_earliest": "1938", 
  "culture": "", 
  "portfolio": "", 
  "paper_support": "", 
  "id": "28764", 
  "catalogue_raisonne": "", 
  "dimensions": "3 1/4 x 4 1/4 in. (8.3 x 10.8 cm)", 
  "title": "Left to Right: Walter Pach, unknown woman, Mrs. Pach, William Glackens, Edith Glackens", 
  "creation_date_latest": "1938", 
  "filename": "A_1_746_r.jpg", 
  "object_name": "photograph", 
  "marks": "", 
  "department": "WCMA", 
  "ULAN": "not found", 
  "medium": "photograph", 
  "description": "", 
  "inscriptions": "", 
  "accession_date": "2013-07-01", 
  "accession_number": "A.1.746", 
  "signed": "", 
  "maker": "unknown"
}