{
  "source_name": "Williams College Museum of Art", 
  "classification": "WCMA-PAINTING", 
  "credit_line": "Anonymous gift", 
  "period": "", 
  "creation_date": "no date", 
  "creation_date_earliest": "0", 
  "culture": "", 
  "portfolio": "", 
  "paper_support": "", 
  "id": "2984", 
  "catalogue_raisonne": "", 
  "dimensions": "Overall: 24 x 19 15/16 in. (61 x 50.7 cm)", 
  "title": "Portrait of a General", 
  "creation_date_latest": "0", 
  "filename": "IMG_92.5.79.jpg", 
  "object_name": "painting", 
  "marks": "", 
  "department": "WCMA", 
  "ULAN": "500125216", 
  "medium": "oil on canvas", 
  "description": "", 
  "inscriptions": "verso lower center on stretcher: [Ryneal art supply label]", 
  "accession_date": "1992-01-01", 
  "accession_number": "92.5.79", 
  "signed": "", 
  "maker": "Anonymous (American)"
}