{
  "source_name": "Williams College Museum of Art", 
  "classification": "WCMA-DRAWING", 
  "credit_line": "Anonymous gift", 
  "period": "", 
  "creation_date": "mid 19th century", 
  "creation_date_earliest": "1825", 
  "culture": "", 
  "portfolio": "", 
  "paper_support": "", 
  "id": "19103", 
  "catalogue_raisonne": "", 
  "dimensions": "Overall: 9 1/16 x 13 1/2 in. (23 x 34.3 cm)", 
  "title": "Entrance of the Val da Compass", 
  "creation_date_latest": "1875", 
  "filename": "", 
  "object_name": "drawing", 
  "marks": "", 
  "department": "WCMA", 
  "ULAN": "not found", 
  "medium": "pencil and white heightening on paper", 
  "description": "", 
  "inscriptions": "l.c. in pencil: Entrance of the Val da Compass", 
  "accession_date": "1978-01-01", 
  "accession_number": "78.17.7", 
  "signed": "", 
  "maker": "Anonymous (British)"
}