{
  "source_name": "Williams College Museum of Art", 
  "classification": "WCMA-PAINTING", 
  "credit_line": "Gift of Mr. and Mrs. Stephen Paine, Sr., parents of Stephen D. Paine, Class of 1954", 
  "period": "", 
  "creation_date": "1967", 
  "creation_date_earliest": "1967", 
  "culture": "", 
  "portfolio": "", 
  "paper_support": "", 
  "id": "9630", 
  "catalogue_raisonne": "", 
  "dimensions": "Overall: 60 1/16 x 60 1/16 in. (152.5 x 152.5 cm)", 
  "title": "Apple", 
  "creation_date_latest": "1967", 
  "filename": "IMG_80.49.jpg", 
  "object_name": "painting", 
  "marks": "", 
  "department": "WCMA", 
  "ULAN": "500011009", 
  "medium": "acrylic on canvas", 
  "description": "", 
  "inscriptions": "verso u.r. in black: don nice/ APPLE/ 60x60/ ACRYLIC/ 1967; verso u.c.: [Alan Stone Galleries label]; verso c.l. on stretcher on label: [Paine Collection label]; verso stamped c.r. & c.l. on canvas: ANJAC PRIMED/ \"GARY\"", 
  "accession_date": "1980-01-01", 
  "accession_number": "80.49", 
  "signed": "", 
  "maker": "Don Nice"
}