{
  "source_name": "Williams College Museum of Art", 
  "classification": "WCMA-Prendergast", 
  "credit_line": "Williams College Museum of Art, Prendergast Archive and Study Center, Gift of Mrs. Charles Prendergast", 
  "period": "", 
  "creation_date": "1941", 
  "creation_date_earliest": "1941", 
  "culture": "", 
  "portfolio": "", 
  "paper_support": "", 
  "id": "28977", 
  "catalogue_raisonne": "", 
  "dimensions": "4 x 5 1/4 in. (10.2 x 13.3 cm)", 
  "title": "Photographs of Charles Prendergast and M.D.C. Crawford in garden at Crooked Mile Road, Westport, CT", 
  "creation_date_latest": "1941", 
  "filename": "A_1_752_C_r.jpg", 
  "object_name": "photograph", 
  "marks": "", 
  "department": "WCMA", 
  "ULAN": "not found", 
  "medium": "photograph", 
  "description": "", 
  "inscriptions": "", 
  "accession_date": "2013-07-01", 
  "accession_number": "A.1.752.C", 
  "signed": "", 
  "maker": "unknown"
}