{
  "source_name": "Williams College Museum of Art", 
  "classification": "WCMA-DRAWING", 
  "credit_line": "Gift of John Alden, Class of 1935", 
  "period": "", 
  "creation_date": "no date", 
  "creation_date_earliest": "1915", 
  "culture": "", 
  "portfolio": "", 
  "paper_support": "", 
  "id": "5189", 
  "catalogue_raisonne": "", 
  "dimensions": "Overall: 13 3/4 x 11 15/16 in. (35 x 30.3 cm)", 
  "title": "Woman with Drum", 
  "creation_date_latest": "1980", 
  "filename": "IMG_80.20.2.jpg", 
  "object_name": "drawing", 
  "marks": "", 
  "department": "WCMA", 
  "ULAN": "500122637", 
  "medium": "acrylic and wash on paper", 
  "description": "", 
  "inscriptions": "l.r. in black paint: --Husain", 
  "accession_date": "1980-01-01", 
  "accession_number": "80.20.2", 
  "signed": "", 
  "maker": "Maqbool Fida Husain"
}