{
  "source_name": "Williams College Museum of Art", 
  "classification": "WCMA-PRINTS", 
  "credit_line": "Museum purchase, Kathryn Hurd Fund and Gift of purchase funds provided by Rosalind and Walter S. Bernheimer, II, Class of 1961", 
  "period": "", 
  "creation_date": "1989", 
  "creation_date_earliest": "1989", 
  "culture": "", 
  "portfolio": "", 
  "paper_support": "", 
  "id": "26597", 
  "catalogue_raisonne": "", 
  "dimensions": "19 x 15 in. (48.3 x 38.1 cm)", 
  "title": "Untitled (from \"Fourteen Etchings\")", 
  "creation_date_latest": "1989", 
  "filename": "M_2009_17_M.jpg", 
  "object_name": "print", 
  "marks": "", 
  "department": "WCMA", 
  "ULAN": "500000039", 
  "medium": "hand-drawn Mylar gravure with various intaglio additions and photogravure printed in one color", 
  "description": "set of 14 prints", 
  "inscriptions": "signed in pencil on frontispiece: 32/65   Terry Winters  1989; u.r. in pencil on each print: TW; l.r. embossed: 13", 
  "accession_date": "2009-12-16", 
  "accession_number": "M.2009.17.M", 
  "signed": "", 
  "maker": "Terry Winters"
}