{
  "source_name": "Williams College Museum of Art", 
  "classification": "WCMA-Prendergast", 
  "credit_line": "Williams College Museum of Art", 
  "period": "", 
  "creation_date": "1967-2000", 
  "creation_date_earliest": "1967", 
  "culture": "", 
  "portfolio": "", 
  "paper_support": "", 
  "id": "29977", 
  "catalogue_raisonne": "", 
  "dimensions": "", 
  "title": "Prendergast Exhibitions and History Miscellaneous", 
  "creation_date_latest": "2000", 
  "filename": "", 
  "object_name": "finding guide", 
  "marks": "", 
  "department": "WCMA", 
  "ULAN": "not found", 
  "medium": "", 
  "description": "", 
  "inscriptions": "", 
  "accession_date": "", 
  "accession_number": "FG.2013.07", 
  "signed": "", 
  "maker": ""
}