{
  "source_name": "Williams College Museum of Art", 
  "classification": "WCMA-ANCIENT", 
  "credit_line": "Gift of Henry N. Flynt, Jr., Class of 1944", 
  "period": "", 
  "creation_date": "400-300 BC", 
  "creation_date_earliest": "-400", 
  "culture": "", 
  "portfolio": "", 
  "paper_support": "", 
  "id": "6286", 
  "catalogue_raisonne": "", 
  "dimensions": "Overall: 2 11/16 x 3 in. (6.8 x 7.6 cm)", 
  "title": "Feeder", 
  "creation_date_latest": "-300", 
  "filename": "94_3_1_a.jpg", 
  "object_name": "vessel", 
  "marks": "", 
  "department": "WCMA", 
  "ULAN": "not found", 
  "medium": "terracotta", 
  "description": "", 
  "inscriptions": "", 
  "accession_date": "1994-04-20", 
  "accession_number": "94.3.1", 
  "signed": "", 
  "maker": "Greek"
}