{
  "source_name": "Williams College Museum of Art", 
  "classification": "WCMA-Prendergast", 
  "credit_line": "Gift of Mrs. Charles Prendergast", 
  "period": "", 
  "creation_date": "ca. 1900-1905", 
  "creation_date_earliest": "1900", 
  "culture": "", 
  "portfolio": "", 
  "paper_support": "", 
  "id": "12807", 
  "catalogue_raisonne": "CMO #841", 
  "dimensions": "Overall: 11 x 15 1/4 in. (27.9 x 38.7 cm)\nframe: 17 7/8 x 22 1/8 x 1 1/4 in. (45.4 x 56.2 x 3.2 cm)", 
  "title": "Surf, Cohasset", 
  "creation_date_latest": "1905", 
  "filename": "91_18_9_r2.jpg", 
  "object_name": "watercolor", 
  "marks": "verso: Sketch of woman in hat. Watercolor brush strokes. #66 Surf, Cohasset 1903, 11 x 15 1/4 in Robert Brady hand(?)", 
  "department": "WCMA", 
  "ULAN": "not found", 
  "medium": "watercolor and pencil on paper", 
  "description": "", 
  "inscriptions": "l.r. in yellow pastel: Prendergast", 
  "accession_date": "1991-01-01", 
  "accession_number": "91.18.9", 
  "signed": "", 
  "maker": "Maurice Brazil Prendergast"
}