{
  "source_name": "Williams College Museum of Art", 
  "classification": "WCMA-PRINTS", 
  "credit_line": "Museum purchase, Kathryn Hurd Fund", 
  "period": "", 
  "creation_date": "1989-1990", 
  "creation_date_earliest": "1989", 
  "culture": "", 
  "portfolio": "", 
  "paper_support": "", 
  "id": "137", 
  "catalogue_raisonne": "", 
  "dimensions": "sheet: 42 7/16 x 29 13/16 in. (107.8 x 75.7 cm)", 
  "title": "D4 (from First Light, Series D)", 
  "creation_date_latest": "1990", 
  "filename": "91_24_D.jpg", 
  "object_name": "print", 
  "marks": "", 
  "department": "WCMA", 
  "ULAN": "not found", 
  "medium": "etching and aquatint on paper", 
  "description": "", 
  "inscriptions": "l.r. in pencil: James Turrell", 
  "accession_date": "1991-01-01", 
  "accession_number": "91.24.D", 
  "signed": "", 
  "maker": "JamesTurrell"
}