{
  "source_name": "Williams College Museum of Art", 
  "classification": "WCMA-PHOTO", 
  "credit_line": "Gift of Mr. and Mrs. Bates Lowry", 
  "period": "", 
  "creation_date": "1868", 
  "creation_date_earliest": "1868", 
  "culture": "", 
  "portfolio": "", 
  "paper_support": "", 
  "id": "14266", 
  "catalogue_raisonne": "", 
  "dimensions": "sheet: 17 1/8 x 20 5/8 in. (43.5 x 52.4 cm)\nimage: 9 3/8 x 11 7/16 in. (23.8 x 29 cm)", 
  "title": "Mahavellipore, near Madras, Basso-relievo on face of granite rocks", 
  "creation_date_latest": "1868", 
  "filename": "78_51_12.jpg", 
  "object_name": "photograph", 
  "marks": "", 
  "department": "WCMA", 
  "ULAN": "500036569", 
  "medium": "albumen print", 
  "description": "Descent of the Ganges, Arjuna's Penance, Mamallapuram, Tamil Nadu", 
  "inscriptions": "no inscription", 
  "accession_date": "1978-01-01", 
  "accession_number": "78.51.12", 
  "signed": "", 
  "maker": "Edmund David Lyon"
}