{
  "source_name": "Williams College Museum of Art", 
  "classification": "WCMA-PRINTS", 
  "credit_line": "Gift of Carl and Barbara Berke", 
  "period": "", 
  "creation_date": "1966", 
  "creation_date_earliest": "1966", 
  "culture": "", 
  "portfolio": "", 
  "paper_support": "", 
  "id": "28314", 
  "catalogue_raisonne": "", 
  "dimensions": "sheet: 27 3/4 x 27 3/4 in. (70.5 x 70.5 cm)\nframe: 27 9/16 x 27 11/16 x 1 1/4 in. (70 x 70.3 x 3.2 cm)", 
  "title": "CTA 102", 
  "creation_date_latest": "1966", 
  "filename": "M_2012_9.jpg", 
  "object_name": "print", 
  "marks": "", 
  "department": "WCMA", 
  "ULAN": "500030657", 
  "medium": "color serigraph on paper", 
  "description": "plastic box type frame", 
  "inscriptions": "two paper gallery labels on verso; pencil inscriptions on verso; stamped numbers on verso top and side members of stretcher", 
  "accession_date": "2012-05-22", 
  "accession_number": "M.2012.9", 
  "signed": "bottom, center:  Vasarely", 
  "maker": "Victor Vasarely"
}