{
  "source_name": "Williams College Museum of Art", 
  "classification": "WCMA-DRAWING", 
  "credit_line": "Anonymous gift", 
  "period": "", 
  "creation_date": "1846", 
  "creation_date_earliest": "1846", 
  "culture": "", 
  "portfolio": "", 
  "paper_support": "", 
  "id": "22461", 
  "catalogue_raisonne": "", 
  "dimensions": "Overall: 6 5/16 x 9 3/4 in. (16.1 x 24.7 cm)", 
  "title": "Tewksbury Cathedral", 
  "creation_date_latest": "1846", 
  "filename": "", 
  "object_name": "drawing", 
  "marks": "", 
  "department": "WCMA", 
  "ULAN": "not found", 
  "medium": "pencil on paper", 
  "description": "", 
  "inscriptions": "l.r. in pencil: Tewksbury/ May 29, 1846", 
  "accession_date": "1978-01-01", 
  "accession_number": "78.17.30", 
  "signed": "", 
  "maker": "Anonymous (British)"
}