{
  "source_name": "Williams College Museum of Art", 
  "classification": "WCMA-PRINTS", 
  "credit_line": "Gift of Frederick M. Myers, Class of 1943", 
  "period": "", 
  "creation_date": "1972", 
  "creation_date_earliest": "1972", 
  "culture": "", 
  "portfolio": "", 
  "paper_support": "", 
  "id": "7347", 
  "catalogue_raisonne": "", 
  "dimensions": "sheet: 39 15/16 x 29 15/16 in. (101.5 x 76.1 cm)", 
  "title": "Frog Cup", 
  "creation_date_latest": "1972", 
  "filename": "81_46_44.jpg", 
  "object_name": "print", 
  "marks": "", 
  "department": "WCMA", 
  "ULAN": "500026883", 
  "medium": "color silkscreen on paper", 
  "description": "", 
  "inscriptions": "l.c. in pencil: 22/71 PRICE`72", 
  "accession_date": "1981-01-01", 
  "accession_number": "81.46.44", 
  "signed": "", 
  "maker": "Kenneth Price"
}