{
  "source_name": "Williams College Museum of Art", 
  "classification": "WCMA-PRINTS", 
  "credit_line": "Museum purchase, Ruth Sabin Weston Fund", 
  "period": "", 
  "creation_date": "no date", 
  "creation_date_earliest": "1607", 
  "culture": "", 
  "portfolio": "", 
  "paper_support": "", 
  "id": "5588", 
  "catalogue_raisonne": "", 
  "dimensions": "Overall: 4 15/16 x 7 1/16 in. (12.5 x 18 cm)", 
  "title": "The Four Windmills", 
  "creation_date_latest": "1677", 
  "filename": "IMG_76.21.jpg", 
  "object_name": "print", 
  "marks": "", 
  "department": "WCMA", 
  "ULAN": "not found", 
  "medium": "etching on paper", 
  "description": "", 
  "inscriptions": "verso l.c. in pencil: [illegible numbers]", 
  "accession_date": "1976-01-01", 
  "accession_number": "76.21", 
  "signed": "", 
  "maker": "Wenceslaus Hollar"
}