{
  "source_name": "Williams College Museum of Art", 
  "classification": "WCMA-Prendergast", 
  "credit_line": "Gift of Mrs. Charles Prendergast", 
  "period": "", 
  "creation_date": "19th-20th century", 
  "creation_date_earliest": "1863", 
  "culture": "", 
  "portfolio": "", 
  "paper_support": "", 
  "id": "28481", 
  "catalogue_raisonne": "", 
  "dimensions": "frame: 16 1/2 x 13 3/4 in. (41.9 x 34.9 cm)", 
  "title": "Frame for \"Sunset\"", 
  "creation_date_latest": "1948", 
  "filename": "86_18_25_fr_r.jpg", 
  "object_name": "frame", 
  "marks": "", 
  "department": "WCMA", 
  "ULAN": "not found", 
  "medium": "gilding and wood", 
  "description": "", 
  "inscriptions": "", 
  "accession_date": "1986-01-01", 
  "accession_number": "86.18.25.FR", 
  "signed": "", 
  "maker": "Attributed to Prendergast"
}