{
  "source_name": "Williams College Museum of Art", 
  "classification": "WCMA-PRINTS", 
  "credit_line": "Gift of Madeleine P. and Harvey R. Plonsker, Class of 1961", 
  "period": "", 
  "creation_date": "1910", 
  "creation_date_earliest": "1910", 
  "culture": "", 
  "portfolio": "", 
  "paper_support": "", 
  "id": "27186", 
  "catalogue_raisonne": "Schiefler/Mosel 136", 
  "dimensions": "13 x 17 in. (33 x 43.2 cm)", 
  "title": "Hamburg, Milde Stimmung (Hamburg, Gentle Atmosphere)", 
  "creation_date_latest": "1910", 
  "filename": "M_2015_25_13.jpg", 
  "object_name": "print", 
  "marks": "", 
  "department": "WCMA", 
  "ULAN": "not found", 
  "medium": "etching and aquatint", 
  "description": "", 
  "inscriptions": "", 
  "accession_date": "2015-12-16", 
  "accession_number": "M.2015.25.13", 
  "signed": "", 
  "maker": "Emil Nolde"
}