{
  "source_name": "Williams College Museum of Art", 
  "classification": "WCMA-PRINTS", 
  "credit_line": "Gift of Joseph Jurist, through the Martin S. Ackerman Foundation", 
  "period": "", 
  "creation_date": "1973", 
  "creation_date_earliest": "1973", 
  "culture": "", 
  "portfolio": "", 
  "paper_support": "", 
  "id": "10022", 
  "catalogue_raisonne": "", 
  "dimensions": "sheet: 31 1/2 x 22 3/4 in. (80 x 57.8 cm)\nimage: 26 5/8 x 15 3/16 in. (67.6 x 38.6 cm)", 
  "title": "Victorian Mirror", 
  "creation_date_latest": "1973", 
  "filename": "", 
  "object_name": "print", 
  "marks": "", 
  "department": "WCMA", 
  "ULAN": "not found", 
  "medium": "color silkscreen on paper", 
  "description": "", 
  "inscriptions": "l.l. in pencil: 28/70; l.r. in pencil: G S Ovenden 73; verso in another hand l.c. in pencil: OOVENDEN[underlined] VICTORIAN MIRROR.", 
  "accession_date": "1981-01-01", 
  "accession_number": "81.15.12", 
  "signed": "", 
  "maker": "Graham Ovenden"
}