{
  "source_name": "Williams College Museum of Art", 
  "classification": "WCMA Reserve Collection", 
  "credit_line": "Possibly(?) Bequest of Katharine F. Bryer White, wife of Walter Leroy White, Class of 1906", 
  "period": "", 
  "creation_date": "no date", 
  "creation_date_earliest": "0", 
  "culture": "", 
  "portfolio": "", 
  "paper_support": "", 
  "id": "20134", 
  "catalogue_raisonne": "", 
  "dimensions": "Overall: 10 in. (25.4 cm)\nrim: 9 1/2 in. (24.1 cm)", 
  "title": "Pot", 
  "creation_date_latest": "0", 
  "filename": "IMG_RC.30.8&9.A&B.jpg", 
  "object_name": "pot", 
  "marks": "", 
  "department": "WCMA", 
  "ULAN": "not found", 
  "medium": "brass", 
  "description": "", 
  "inscriptions": "", 
  "accession_date": "1959", 
  "accession_number": "RC.30.9.A", 
  "signed": "", 
  "maker": "American"
}