{
  "source_name": "Williams College Museum of Art", 
  "classification": "WCMA-DRAWING", 
  "credit_line": "Gift of Robert B. Meyersburg, Class of 1937", 
  "period": "", 
  "creation_date": "July 25, 1963", 
  "creation_date_earliest": "1963", 
  "culture": "", 
  "portfolio": "", 
  "paper_support": "", 
  "id": "17282", 
  "catalogue_raisonne": "", 
  "dimensions": "image: 25 x 39 3/4 in. (63.5 x 101 cm)\nframe: 26 x 40 1/2 x 1 3/16 in. (66 x 102.9 x 3 cm)", 
  "title": "Untitled", 
  "creation_date_latest": "1963", 
  "filename": "M_2004_17_4.jpg", 
  "object_name": "drawing", 
  "marks": "", 
  "department": "WCMA", 
  "ULAN": "500015402", 
  "medium": "oil on paper", 
  "description": "", 
  "inscriptions": "Signed in lower left: For Sybil- July 25, 1963 When we should have had the big Washington D.C. party David Rebecca Candida.  Embossed in upper left corner: Arches", 
  "accession_date": "2004-10-06", 
  "accession_number": "M.2004.17.4", 
  "signed": "", 
  "maker": "David Smith"
}