{
  "source_name": "Williams College Museum of Art", 
  "classification": "WCMA-Prendergast", 
  "credit_line": "Bequest of Mrs. Charles Prendergast", 
  "period": "", 
  "creation_date": "ca. 1907", 
  "creation_date_earliest": "1907", 
  "culture": "", 
  "portfolio": "", 
  "paper_support": "", 
  "id": "13891", 
  "catalogue_raisonne": "CMO #873", 
  "dimensions": "(sight): 13 x 19 1/4 in. (33 x 48.9 cm)", 
  "title": "Gloucester Harbor", 
  "creation_date_latest": "1907", 
  "filename": "95_4_81_r1.jpg", 
  "object_name": "watercolor", 
  "marks": "", 
  "department": "WCMA", 
  "ULAN": "not found", 
  "medium": "watercolor and pencil on paper", 
  "description": "", 
  "inscriptions": "l.r. in black: Prendergast", 
  "accession_date": "1995-03-03", 
  "accession_number": "95.4.81", 
  "signed": "", 
  "maker": "Maurice Brazil Prendergast"
}