{
  "source_name": "Williams College Museum of Art", 
  "classification": "WCMA-PRINTS", 
  "credit_line": "Museum purchase", 
  "period": "", 
  "creation_date": "no date", 
  "creation_date_earliest": "1887", 
  "culture": "", 
  "portfolio": "", 
  "paper_support": "", 
  "id": "11795", 
  "catalogue_raisonne": "", 
  "dimensions": "sheet: 15 1/16 x 11 1/8 in. (38.3 x 28.2 cm)\nplate: 11 x 8 7/16 in. (28 x 21.5 cm)", 
  "title": "The Revelation of Nordriov (from Gogol's \"Dead Souls\")", 
  "creation_date_latest": "1957", 
  "filename": "", 
  "object_name": "print", 
  "marks": "", 
  "department": "WCMA", 
  "ULAN": "500115354", 
  "medium": "etching on paper", 
  "description": "", 
  "inscriptions": "l.c. in pencil: LXIV Revelations of Nordriov 42-1-64 Rln $20.--", 
  "accession_date": "1957-01-01", 
  "accession_number": "57.19", 
  "signed": "", 
  "maker": "Marc Chagall"
}