{
  "source_name": "Williams College Museum of Art", 
  "classification": "WCMA-DRAWING", 
  "credit_line": "Gift of Dr. Robert Erwin Jones, Class of 1952", 
  "period": "", 
  "creation_date": "1789", 
  "creation_date_earliest": "1789", 
  "culture": "", 
  "portfolio": "", 
  "paper_support": "", 
  "id": "21280", 
  "catalogue_raisonne": "", 
  "dimensions": "Overall: 11 3/8 x 4 3/4 in. (28.9 x 12.1 cm)", 
  "title": "The Raising of Lazarus", 
  "creation_date_latest": "1789", 
  "filename": "84_33_6.jpg", 
  "object_name": "drawing", 
  "marks": "", 
  "department": "WCMA", 
  "ULAN": "500026989", 
  "medium": "pen and ink with brown washes over pencil on paper", 
  "description": "", 
  "inscriptions": "l.r. in ink: B. W. 1789 Windsor; verso l.l. in pencil: 24", 
  "accession_date": "1984-01-01", 
  "accession_number": "84.33.6", 
  "signed": "", 
  "maker": "Benjamin West"
}