{
  "source_name": "Williams College Museum of Art", 
  "classification": "WCMA-AFRICAN", 
  "credit_line": "Anonymous gift", 
  "period": "", 
  "creation_date": "20th century", 
  "creation_date_earliest": "1960", 
  "culture": "Yoruba, possibly Ilorin", 
  "portfolio": "", 
  "paper_support": "", 
  "id": "3474", 
  "catalogue_raisonne": "", 
  "dimensions": "Overall: 69 1/2 x 46 7/8 in. (176.5 x 119 cm)", 
  "title": "Aso oke men's weave cloth (possibly mantle, wrapper or blanket)", 
  "creation_date_latest": "1969", 
  "filename": "94_1_106.jpg", 
  "object_name": "textile | costume", 
  "marks": "", 
  "department": "WCMA", 
  "ULAN": "not found", 
  "medium": "cotton | rayon?", 
  "description": "maroon and white with blue pin stripe; float weave technique on cotton/rayon? Woven on double-heddle, narrow-band, horizontal treadle loom", 
  "inscriptions": "no inscription", 
  "accession_date": "1994-01-01", 
  "accession_number": "94.1.106", 
  "signed": "", 
  "maker": "Yoruba People"
}