{
  "source_name": "Williams College Museum of Art", 
  "classification": "WCMA-DRAWING", 
  "credit_line": "Gift of the artist", 
  "period": "", 
  "creation_date": "no date", 
  "creation_date_earliest": "0", 
  "culture": "", 
  "portfolio": "", 
  "paper_support": "", 
  "id": "5891", 
  "catalogue_raisonne": "", 
  "dimensions": "", 
  "title": "Cartoon Drawings", 
  "creation_date_latest": "0", 
  "filename": "", 
  "object_name": "drawings", 
  "marks": "", 
  "department": "WCMA", 
  "ULAN": "500097474", 
  "medium": "", 
  "description": "", 
  "inscriptions": "", 
  "accession_date": "1952-01-01", 
  "accession_number": "52.7", 
  "signed": "", 
  "maker": "John Harmon Cassel"
}