{
  "source_name": "Williams College Museum of Art", 
  "classification": "WCMA-PHOTO", 
  "credit_line": "Gift of Martin Ford Puris", 
  "period": "", 
  "creation_date": "1969", 
  "creation_date_earliest": "1969", 
  "culture": "", 
  "portfolio": "", 
  "paper_support": "", 
  "id": "22401", 
  "catalogue_raisonne": "", 
  "dimensions": "sheet: 13 15/16 x 10 7/8 in. (35.4 x 27.7 cm)\nimage: 12 3/8 x 8 1/8 in. (31.5 x 20.7 cm)", 
  "title": "Knife, Fork, Spoon (from \"Somnambulist\")", 
  "creation_date_latest": "1969", 
  "filename": "84_6_G.jpg", 
  "object_name": "photograph", 
  "marks": "", 
  "department": "WCMA", 
  "ULAN": "500094623", 
  "medium": "gelatin silver print", 
  "description": "", 
  "inscriptions": "no inscription", 
  "accession_date": "1984-01-01", 
  "accession_number": "84.6.G", 
  "signed": "", 
  "maker": "Ralph Gibson"
}