{
  "source_name": "Williams College Museum of Art", 
  "classification": "WCMA-EASTERN", 
  "credit_line": "Gift of Peter J. and Jane B. Stewart\n", 
  "period": "", 
  "creation_date": "early 19th century", 
  "creation_date_earliest": "1800", 
  "culture": "Indian", 
  "portfolio": "", 
  "paper_support": "", 
  "id": "17763", 
  "catalogue_raisonne": "", 
  "dimensions": "frame: 13 3/4 x 16 1/4 in. (34.9 x 41.3 cm)\nsheet: 9 11/16 x 12 1/4 in. (24.6 x 31.1 cm)", 
  "title": "Two priests worshipping Krishna with a variety of religious objects around", 
  "creation_date_latest": "1850", 
  "filename": "M_2006_2_26.jpg", 
  "object_name": "watercolor", 
  "marks": "", 
  "department": "WCMA", 
  "ULAN": "not found", 
  "medium": "opaque watercolor on paper", 
  "description": "", 
  "inscriptions": "", 
  "accession_date": "2006-06-30", 
  "accession_number": "M.2006.2.26", 
  "signed": "", 
  "maker": "Kashmir"
}