{
  "source_name": "Williams College Museum of Art", 
  "classification": "WCMA-Prendergast", 
  "credit_line": "Bequest of Mrs. Charles Prendergast", 
  "period": "", 
  "creation_date": "ca. 1910-1913", 
  "creation_date_earliest": "1910", 
  "culture": "", 
  "portfolio": "", 
  "paper_support": "", 
  "id": "19130", 
  "catalogue_raisonne": "CMO #1130", 
  "dimensions": "Overall: 13 3/4 x 9 3/4 in. (34.9 x 24.8 cm)\nOverall1: 13 3/4 x 9 3/4 in. (34.9 x 24.8 cm)", 
  "title": "Egyptian Dancers", 
  "creation_date_latest": "1913", 
  "filename": "95_4_13_r.jpg", 
  "object_name": "watercolor", 
  "marks": "", 
  "department": "WCMA", 
  "ULAN": "not found", 
  "medium": "watercolor and pencil on paper", 
  "description": "", 
  "inscriptions": "modern dancers sketch; verso l.r. in purple paint reinforced with black ink (in Charles Prendergast's hand): Prendergast/PER CP", 
  "accession_date": "1995-03-03", 
  "accession_number": "95.4.13", 
  "signed": "", 
  "maker": "Maurice Brazil Prendergast"
}