{
  "source_name": "Williams College Museum of Art", 
  "classification": "WCMA-PAINTING", 
  "credit_line": "Gift of the Artist in Honor of Mr. and Mrs. Marshall S. Hannock, Class of 1942", 
  "period": "", 
  "creation_date": "1991-1994", 
  "creation_date_earliest": "1991", 
  "culture": "", 
  "portfolio": "", 
  "paper_support": "", 
  "id": "3809", 
  "catalogue_raisonne": "", 
  "dimensions": "Overall: 7 5/8 x 10 5/8 in. (19.4 x 27 cm)\nframe: 13 3/8 x 16 1/8 x 1 7/8 in. (34 x 41 x 4.8 cm)", 
  "title": "Study: Oxbow, After Church, After Cole, Flooded (Cool Ground) Flooded River for M. and E. Hannock)", 
  "creation_date_latest": "1994", 
  "filename": "94_4.jpg", 
  "object_name": "painting", 
  "marks": "", 
  "department": "WCMA", 
  "ULAN": "500330770", 
  "medium": "polished oil on canvas", 
  "description": "", 
  "inscriptions": "l.r. blue paint: Stephen Hannock 1994; verso black crayon: Merry Christmas & Love   3/92;for Mom and Dad;From: SWH;Hannock 12/93; verso paper exhibition label: [Salander-O'Reilly Galleries, Inc.]", 
  "accession_date": "1994-04-20", 
  "accession_number": "94.4", 
  "signed": "", 
  "maker": "Stephen Hannock"
}