{
  "source_name": "Williams College Museum of Art", 
  "classification": "WCMA-ANCIENT", 
  "credit_line": "Anonymous gift", 
  "period": "", 
  "creation_date": "no date", 
  "creation_date_earliest": "0", 
  "culture": "", 
  "portfolio": "", 
  "paper_support": "", 
  "id": "9556", 
  "catalogue_raisonne": "", 
  "dimensions": "Overall: 1/2 x 5/16 x 7/16 in. (1.2 x 0.8 x 1.1 cm)", 
  "title": "Bull Head Amulet", 
  "creation_date_latest": "0", 
  "filename": "93_1_14_O_a.jpg", 
  "object_name": "amulet", 
  "marks": "", 
  "department": "WCMA", 
  "ULAN": "not found", 
  "medium": "stone?", 
  "description": "pink sandstone?", 
  "inscriptions": "no inscription", 
  "accession_date": "1993-01-01", 
  "accession_number": "93.1.14.O", 
  "signed": "", 
  "maker": "Egyptian"
}