{
  "source_name": "Williams College Museum of Art", 
  "classification": "WCMA-PAINTING", 
  "credit_line": "Anonymous gift", 
  "period": "", 
  "creation_date": "1891", 
  "creation_date_earliest": "1891", 
  "culture": "", 
  "portfolio": "", 
  "paper_support": "", 
  "id": "9298", 
  "catalogue_raisonne": "", 
  "dimensions": "frame: 39 3/8 x 34 7/16 in. (100 x 87.5 cm)", 
  "title": "Portrait of Frederick Ferris Thompson (1836-1899), Class of 1856, College Trustee 1886-1899, Benefactor", 
  "creation_date_latest": "1891", 
  "filename": "", 
  "object_name": "painting", 
  "marks": "", 
  "department": "WCMA", 
  "ULAN": "not found", 
  "medium": "oil on canvas", 
  "description": "", 
  "inscriptions": "l.l. in red: J.H.Littlefield/ 1891; verso u.r. on stretcher: [two old WCMA labels]; verso c. in pencil: J.H. Littlefield/ New York 1891/ Portrait from Life of/ Frederick F. Thompson", 
  "accession_date": "", 
  "accession_number": "WP.55", 
  "signed": "", 
  "maker": "John Harrison Littlefield"
}