{
  "source_name": "Williams College Museum of Art", 
  "classification": "WCMA-Prendergast", 
  "credit_line": "Williams College Museum of Art, Prendergast Archive and Study Center, Gift of Mrs. Charles Prendergast", 
  "period": "", 
  "creation_date": "19th-20th century", 
  "creation_date_earliest": "1863", 
  "culture": "", 
  "portfolio": "", 
  "paper_support": "", 
  "id": "5528", 
  "catalogue_raisonne": "", 
  "dimensions": "Overall: 7 1/2 x 13/16 x 13/16 in. (19 x 2 x 2 cm)", 
  "title": "carving tool", 
  "creation_date_latest": "1948", 
  "filename": "A_1_2_aa.jpg", 
  "object_name": "carving tool", 
  "marks": "", 
  "department": "WCMA", 
  "ULAN": "not found", 
  "medium": "", 
  "description": "", 
  "inscriptions": "cast in steel on blade: [two symbols, one of a buck] BROS/STEEL; cast in steel on blade: 1", 
  "accession_date": "1998-12-11", 
  "accession_number": "A.1.2.AA", 
  "signed": "", 
  "maker": "Charles Prendergast"
}