{
  "source_name": "Williams College Museum of Art", 
  "classification": "WCMA-PRINTS", 
  "credit_line": "Anonymous gift", 
  "period": "", 
  "creation_date": "1971", 
  "creation_date_earliest": "1971", 
  "culture": "", 
  "portfolio": "", 
  "paper_support": "", 
  "id": "22379", 
  "catalogue_raisonne": "", 
  "dimensions": "sheet: 14 15/16 x 19 in. (37.9 x 48.3 cm)\nimage: 9 15/16 x 14 in. (25.3 x 35.6 cm)", 
  "title": "Lower Right", 
  "creation_date_latest": "1971", 
  "filename": "IMG_78.22.34.jpg", 
  "object_name": "print", 
  "marks": "", 
  "department": "WCMA", 
  "ULAN": "500042016", 
  "medium": "lithograph", 
  "description": "", 
  "inscriptions": "l.l. in pencil: 27/50; l.c. in pencil: lower Right; l.r. in pencil; Emilio Sanchez", 
  "accession_date": "1978-01-01", 
  "accession_number": "78.22.34", 
  "signed": "", 
  "maker": "Emilio Sanchez"
}