{
  "source_name": "Williams College Museum of Art", 
  "classification": "WCMA-PRINTS", 
  "credit_line": "Gift of Mabel Nast Crawford and Cyril Nast", 
  "period": "", 
  "creation_date": "April 10, 1892", 
  "creation_date_earliest": "1892", 
  "culture": "", 
  "portfolio": "", 
  "paper_support": "", 
  "id": "7665", 
  "catalogue_raisonne": "", 
  "dimensions": "Overall: 23 3/16 x 17 1/4 in. (58.9 x 43.8 cm)", 
  "title": "Chicago to New York & Philadelphia\nThe Typical Figure of New York Ought to Be Rip Van Winkle", 
  "creation_date_latest": "1892", 
  "filename": "IMG_49.17.83.jpg", 
  "object_name": "print | newspaper", 
  "marks": "", 
  "department": "WCMA", 
  "ULAN": "500026650", 
  "medium": "print on paper", 
  "description": "", 
  "inscriptions": "both cartoons signed in plate", 
  "accession_date": "1949-01-01", 
  "accession_number": "49.17.83", 
  "signed": "", 
  "maker": "Thomas Nast"
}