{
  "source_name": "Williams College Museum of Art", 
  "classification": "WCMA-SCULPTURE", 
  "credit_line": "Gift of Peter and Julie Jenks Zorach", 
  "period": "", 
  "creation_date": "no date", 
  "creation_date_earliest": "1887", 
  "culture": "", 
  "portfolio": "", 
  "paper_support": "", 
  "id": "8644", 
  "catalogue_raisonne": "", 
  "dimensions": "Overall: 29 1/2 x 55 7/8 in. (75 x 142 cm)", 
  "title": "Newborn", 
  "creation_date_latest": "1966", 
  "filename": "IMG_87.4.cs.jpg", 
  "object_name": "sculpture", 
  "marks": "", 
  "department": "WCMA", 
  "ULAN": "500003603", 
  "medium": "bronze", 
  "description": "", 
  "inscriptions": "", 
  "accession_date": "1987-01-01", 
  "accession_number": "87.4", 
  "signed": "", 
  "maker": "William Zorach"
}