{
  "source_name": "Williams College Museum of Art", 
  "classification": "WCMA-DRAWING", 
  "credit_line": "Gift of Frank J. Mather, Jr., Class of 1889", 
  "period": "", 
  "creation_date": "1700", 
  "creation_date_earliest": "1700", 
  "culture": "", 
  "portfolio": "", 
  "paper_support": "", 
  "id": "4715", 
  "catalogue_raisonne": "", 
  "dimensions": "Overall: 12 1/16 x 10 in. (30.6 x 25.4 cm)", 
  "title": "Death of Adonis (?)", 
  "creation_date_latest": "1700", 
  "filename": "IMG_28.5.jpg", 
  "object_name": "drawing", 
  "marks": "", 
  "department": "WCMA", 
  "ULAN": "not found", 
  "medium": "pen and ink with wash on paper", 
  "description": "", 
  "inscriptions": "l.r. in ink: stamp; verso l.c. in pencil: 8  8. L. Giondano [?]", 
  "accession_date": "1928-01-01", 
  "accession_number": "28.5", 
  "signed": "", 
  "maker": "Anonymous (Italian)"
}