{
  "source_name": "Williams College Museum of Art", 
  "classification": "WCMA-PRINTS", 
  "credit_line": "Bequest of Jane T. Ritchie", 
  "period": "", 
  "creation_date": "no date", 
  "creation_date_earliest": "1859", 
  "culture": "", 
  "portfolio": "", 
  "paper_support": "", 
  "id": "10500", 
  "catalogue_raisonne": "", 
  "dimensions": "sheet: 12 13/16 x 9 in. (32.5 x 22.8 cm)\nplate: 9 15/16 x 6 15/16 in. (25.3 x 17.6 cm)", 
  "title": "Portrait of Henry Newbolt", 
  "creation_date_latest": "1921", 
  "filename": "IMG_85.46.25.jpg", 
  "object_name": "print", 
  "marks": "", 
  "department": "WCMA", 
  "ULAN": "not found", 
  "medium": "etching on paper", 
  "description": "", 
  "inscriptions": "l.r. in pencil: WmStrang; lower edge in pencil: W.Strang. Portrait Henry Newbolt. N.344.  8400008.  WM.STRANG. \"Henry Newbolt\"; verso l.l. in pencil: iii9; verso l.c. in pencil: 1306", 
  "accession_date": "1985-01-01", 
  "accession_number": "85.46.25", 
  "signed": "", 
  "maker": "William Strang"
}